milesToMuppets/__init__.py
milesToMuppets/data.py
milesToMuppets/functions.py
milesToMuppets/helpers.py
milesToMuppets/muppet.py
milesToMuppets/txt/links.txt
milesToMuppets/txt/notes.txt
milestomuppets-0.0.19.dist-info/METADATA
milestomuppets-0.0.19.dist-info/WHEEL
milestomuppets-0.0.19.dist-info/licenses/LICENSE
milestomuppets-0.0.19.dist-info/RECORD
