Metadata-Version: 2.3
Name: MilesToMuppets
Version: 0.0.19
Summary: A conversion package to convert Miles to how many songs you can listen to from the Muppets Album
Project-URL: Homepage, https://github.com/SketchedDoughnut/miles-to-muppets
Project-URL: Issues, https://github.com/SketchedDoughnut/miles-to-muppets/issues
Author-email: Sketched Doughnut <sketcheddoughnut@gmail.com>
License-File: LICENSE
Classifier: License :: OSI Approved :: Apache Software License
Classifier: Operating System :: OS Independent
Classifier: Programming Language :: Python :: 3
Requires-Python: >=3.8
Requires-Dist: requests
